qiskit_medusa/__init__.py
qiskit_medusa/backend.py
qiskit_medusa/libmedusa.so
qiskit_medusa/provider.py
qiskit_medusa/simulator_core.py
qiskit_medusa.libs/libgmp-b6ddd92b.so.10.5.0
qiskit_medusa-0.1.0.dist-info/METADATA
qiskit_medusa-0.1.0.dist-info/WHEEL
qiskit_medusa-0.1.0.dist-info/RECORD
qiskit_medusa-0.1.0.dist-info/sboms/auditwheel.cdx.json
