Metadata-Version: 2.2
Name: qiskit-medusa
Version: 0.1.0
Summary: A high-performance MTBDD quantum simulator for Qiskit
Author-Email: Roman Janota <janotaroman02@gmail.com>
Requires-Python: >=3.8
Requires-Dist: qiskit>=1.0
Requires-Dist: numpy>=1.20
Provides-Extra: dev
Requires-Dist: pytest; extra == "dev"
Requires-Dist: black; extra == "dev"
Requires-Dist: pylint; extra == "dev"
